winterapi/__init__.py
winterapi/base_api.py
winterapi/configure_tests.py
winterapi/credentials.py
winterapi/endpoints.py
winterapi/fidelius.py
winterapi/messenger.py
winterapi-1.5.0.dist-info/LICENSE
winterapi-1.5.0.dist-info/METADATA
winterapi-1.5.0.dist-info/WHEEL
winterapi-1.5.0.dist-info/top_level.txt
winterapi-1.5.0.dist-info/RECORD
