Metadata-Version: 2.2
Name: winterapi
Version: 1.5.0
Author-email: Robert Stein <rdstein@caltech.edu>
License: MIT
Project-URL: Homepage, https://github.com/winter-telescope/winterapi
Classifier: Programming Language :: Python :: 3
Classifier: Programming Language :: Python :: 3.10
Classifier: Programming Language :: Python :: 3.11
Classifier: Intended Audience :: Science/Research
Classifier: Intended Audience :: End Users/Desktop
Classifier: Intended Audience :: Developers
Classifier: Natural Language :: English
Classifier: Topic :: Scientific/Engineering
Classifier: Topic :: Scientific/Engineering :: Astronomy
Classifier: Topic :: Scientific/Engineering :: Physics
Classifier: Operating System :: POSIX
Classifier: Operating System :: Unix
Classifier: Operating System :: MacOS
Requires-Python: >=3.10
License-File: LICENSE
Requires-Dist: pandas
Requires-Dist: packaging
Requires-Dist: keyring
Requires-Dist: cryptography
Requires-Dist: pre-commit
Requires-Dist: jupyter
Requires-Dist: backoff
Requires-Dist: pydantic
Requires-Dist: wintertoo>=1.8.0
Provides-Extra: dev
Requires-Dist: black==24.4.2; extra == "dev"
Requires-Dist: isort==5.13.2; extra == "dev"
Requires-Dist: pylint==3.2.2; extra == "dev"
Requires-Dist: coveralls; extra == "dev"
